imwatermark/__init__.py
imwatermark/dwt.py
imwatermark/dwtDctSvd.py
imwatermark/dwtDctSvdOptimized.py
imwatermark/dwtSvd.py
imwatermark/maxDct.py
imwatermark/maxDctOptimized.py
imwatermark/rivaGan.py
imwatermark/rivagan_decoder.onnx
imwatermark/rivagan_encoder.onnx
imwatermark/watermark.py
invisible_watermark_gpu-0.2.4.data/scripts/invisible-watermark
tests/__init__.py
tests/test_watermarking.py
tests/test_wavelets.py
invisible_watermark_gpu-0.2.4.dist-info/LICENSE
invisible_watermark_gpu-0.2.4.dist-info/METADATA
invisible_watermark_gpu-0.2.4.dist-info/WHEEL
invisible_watermark_gpu-0.2.4.dist-info/top_level.txt
invisible_watermark_gpu-0.2.4.dist-info/RECORD
