Metadata-Version: 2.1
Name: invisible-watermark-gpu
Version: 0.2.4
Summary: GPU adaptation for the library for creating and decoding invisible image watermarks
Home-page: https://github.com/Stability-AI/invisible-watermark-gpu
Author: Will Drevo
Author-email: will.drevo@stability.ai
Classifier: Programming Language :: Python :: 3
Classifier: License :: OSI Approved :: MIT License
Classifier: Operating System :: POSIX :: Linux
Requires-Python: >=3.6
License-File: LICENSE
Requires-Dist: opencv-python-headless ==4.8.0.76
Requires-Dist: torch >=2.0.0
Requires-Dist: Pillow >=6.0.0
Requires-Dist: PyWavelets >=1.1.1
Requires-Dist: numpy >=1.17.0
Requires-Dist: pycudwt-multitarget ==1.0.5
Requires-Dist: pytest
